{
    "initialCoverSize": 81,
    "times": [
        2203578,
        5325053,
        8480468,
        11515750,
        14805462,
        17858684,
        22226578,
        25391114,
        28619372,
        31747264,
        34844597,
        39204581,
        43353505,
        46771004,
        49899675,
        53064105,
        56258199,
        59353151,
        62607842,
        65873815,
        69182798,
        72393567,
        75567307,
        78757992
    ],
    "solution": [
        {
            "x": 0,
            "cycle": "0_NL 1_BE,0_NL 0_NL"
        },
        {
            "x": 0,
            "cycle": "0_NL 2_DK,0_NL 0_NL"
        },
        {
            "x": 0,
            "cycle": "0_NL 3_PL 0_NL 0_NL"
        },
        {
            "x": 0,
            "cycle": "0_NL 9_IT 0_NL 0_NL"
        },
        {
            "x": 0,
            "cycle": "0_NL 18_PT 0_NL 0_NL"
        },
        {
            "x": 0,
            "cycle": "0_NL 32_EE 0_NL 0_NL"
        },
        {
            "x": 0,
            "cycle": "0_NL,2_DK 3_PL 0_NL"
        },
        {
            "x": 0,
            "cycle": "0_NL 25_RU 0_NL 0_NL"
        },
        {
            "x": 0,
            "cycle": "0_NL 26_IS 0_NL 0_NL"
        },
        {
            "x": 0,
            "cycle": "0_NL 29_NO 0_NL 0_NL"
        },
        {
            "x": 0,
            "cycle": "0_NL 30_SE 0_NL 0_NL"
        },
        {
            "x": 0,
            "cycle": "0_NL 24_LT 0_NL 0_NL"
        },
        {
            "x": 0,
            "cycle": "0_NL 3_PL 5_CZ 0_NL"
        },
        {
            "x": 0,
            "cycle": "0_NL 3_PL 2_DK,0_NL"
        },
        {
            "x": 0,
            "cycle": "0_NL 5_CZ 0_NL 0_NL"
        },
        {
            "x": 0,
            "cycle": "0_NL 6_LU 0_NL 0_NL"
        },
        {
            "x": 0,
            "cycle": "0_NL 8_CH 0_NL 0_NL"
        },
        {
            "x": 0,
            "cycle": "0_NL 12_IL 0_NL 0_NL"
        },
        {
            "x": 0,
            "cycle": "0_NL 10_GR 0_NL 0_NL"
        },
        {
            "x": 1,
            "cycle": "0_NL 3_PL 25_RU 0_NL"
        },
        {
            "x": 0,
            "cycle": "0_NL 5_CZ 3_PL 0_NL"
        },
        {
            "x": 0,
            "cycle": "0_NL 15_RO 0_NL 0_NL"
        },
        {
            "x": 0,
            "cycle": "0_NL 7_FR 0_NL 0_NL"
        },
        {
            "x": 0,
            "cycle": "0_NL 7_FR 8_CH 0_NL"
        },
        {
            "x": 1,
            "cycle": "0_NL,1_BE 19_ES 0_NL"
        },
        {
            "x": 0,
            "cycle": "0_NL 6_LU 27_IE 0_NL"
        },
        {
            "x": 0,
            "cycle": "0_NL 8_CH 7_FR 0_NL"
        },
        {
            "x": 0,
            "cycle": "0_NL 3_PL 9_IT 0_NL"
        },
        {
            "x": 0,
            "cycle": "0_NL 19_ES 0_NL 0_NL"
        },
        {
            "x": 0,
            "cycle": "0_NL 9_IT 3_PL 0_NL"
        },
        {
            "x": 0,
            "cycle": "0_NL 7_FR 10_GR 0_NL"
        },
        {
            "x": 0,
            "cycle": "0_NL 11_CY 0_NL 0_NL"
        },
        {
            "x": 0,
            "cycle": "0_NL 9_IT 18_PT 0_NL"
        },
        {
            "x": 0,
            "cycle": "0_NL 9_IT 17_SK 0_NL"
        },
        {
            "x": 0,
            "cycle": "0_NL 10_GR 7_FR 0_NL"
        },
        {
            "x": 0,
            "cycle": "0_NL 10_GR 11_CY 0_NL"
        },
        {
            "x": 0,
            "cycle": "0_NL 14_TR 0_NL 0_NL"
        },
        {
            "x": 0,
            "cycle": "0_NL 11_CY 10_GR 0_NL"
        },
        {
            "x": 0,
            "cycle": "0_NL 14_TR 3_PL 0_NL"
        },
        {
            "x": 0,
            "cycle": "0_NL 3_PL 14_TR 0_NL"
        },
        {
            "x": 1,
            "cycle": "0_NL 15_RO 7_FR 0_NL"
        },
        {
            "x": 0,
            "cycle": "0_NL 5_CZ 20_BG 0_NL"
        },
        {
            "x": 0,
            "cycle": "0_NL 3_PL 21_HR 0_NL"
        },
        {
            "x": 0,
            "cycle": "0_NL 16_HU 23_AT 0_NL"
        },
        {
            "x": 0,
            "cycle": "0_NL 18_PT 3_PL 0_NL"
        },
        {
            "x": 0,
            "cycle": "0_NL 18_PT 6_LU 0_NL"
        },
        {
            "x": 0,
            "cycle": "0_NL 18_PT 9_IT 0_NL"
        },
        {
            "x": 0,
            "cycle": "0_NL 7_FR 15_RO 0_NL"
        },
        {
            "x": 0,
            "cycle": "0_NL 9_IT 16_HU 0_NL"
        },
        {
            "x": 0,
            "cycle": "0_NL 21_HR 3_PL 0_NL"
        },
        {
            "x": 0,
            "cycle": "0_NL 17_SK 9_IT 0_NL"
        },
        {
            "x": 0,
            "cycle": "0_NL 3_PL 33_LV 0_NL"
        },
        {
            "x": 1,
            "cycle": "0_NL 25_RU 3_PL 0_NL"
        },
        {
            "x": 1,
            "cycle": "0_NL 29_NO 30_SE 0_NL"
        },
        {
            "x": 1,
            "cycle": "0_NL 30_SE 29_NO 0_NL"
        },
        {
            "x": 0,
            "cycle": "0_NL 31_FI 0_NL 0_NL"
        },
        {
            "x": 0,
            "cycle": "0_NL 33_LV 0_NL 0_NL"
        },
        {
            "x": 0,
            "cycle": "0_NL 32_EE 24_LT 0_NL"
        },
        {
            "x": 1,
            "cycle": "0_NL 19_ES 1_BE 0_NL"
        },
        {
            "x": 1,
            "cycle": "0_NL 21_HR 11_CY 0_NL"
        },
        {
            "x": 0,
            "cycle": "0_NL 26_IS 12_IL 0_NL"
        },
        {
            "x": 1,
            "cycle": "0_NL 11_CY 21_HR 0_NL"
        },
        {
            "x": 0,
            "cycle": "0_NL 31_FI 3_PL 0_NL"
        },
        {
            "x": 0,
            "cycle": "0_NL 15_RO 11_CY 0_NL"
        },
        {
            "x": 1,
            "cycle": "0_NL 33_LV 14_TR 0_NL"
        },
        {
            "x": 0,
            "cycle": "0_NL 11_CY 15_RO 0_NL"
        },
        {
            "x": 0,
            "cycle": "0_NL 27_IE 8_CH 0_NL"
        },
        {
            "x": 0,
            "cycle": "0_NL 19_ES 17_SK 0_NL"
        },
        {
            "x": 0,
            "cycle": "0_NL 25_RU 9_IT 0_NL"
        },
        {
            "x": 1,
            "cycle": "0_NL 27_IE 15_RO 0_NL"
        },
        {
            "x": 1,
            "cycle": "0_NL 18_PT 17_SK 0_NL"
        },
        {
            "x": 0,
            "cycle": "0_NL 6_LU 26_IS 0_NL"
        },
        {
            "x": 1,
            "cycle": "0_NL 12_IL 31_FI 0_NL"
        },
        {
            "x": 1,
            "cycle": "0_NL 17_SK 18_PT 0_NL"
        },
        {
            "x": 1,
            "cycle": "0_NL 14_TR 33_LV 0_NL"
        },
        {
            "x": 0,
            "cycle": "0_NL 7_FR 2_DK 0_NL"
        },
        {
            "x": 0,
            "cycle": "0_NL 25_RU 7_FR 0_NL"
        },
        {
            "x": 1,
            "cycle": "0_NL 26_IS 7_FR 0_NL"
        },
        {
            "x": 0,
            "cycle": "0_NL 8_CH 27_IE 0_NL"
        },
        {
            "x": 0,
            "cycle": "0_NL 9_IT 25_RU 0_NL"
        },
        {
            "x": 0,
            "cycle": "0_NL 19_ES 2_DK 0_NL"
        }
    ],
    "values": [
        29,
        28,
        26,
        24,
        22,
        22,
        22,
        21,
        21,
        21,
        20,
        20,
        20,
        19.5,
        19.5,
        18.5,
        17.5,
        16.5,
        16.5,
        16,
        16,
        16,
        16,
        16
    ],
    "initialCoverSeg": 4,
    "runtime": 460110,
    "lpBound": 16
}