{
    "originalCover": {
        "runtime": 4434684,
        "cycles": [
            "11_Stockholm 0_Prague 1 11_Stockholm",
            "11_Stockholm 6_Geneva 0_Prague 0_Prague 11_Stockholm",
            "11_Stockholm 0_Prague 5_Madrid 0_Prague 11_Stockholm",
            "11_Stockholm 0_Prague 2_Hamburg 0_Prague 11_Stockholm",
            "11_Stockholm 0_Prague 2_Hamburg 8",
            "26 2_Hamburg 0_Prague 11_Stockholm",
            "11_Stockholm 6_Geneva 4_Dubai 6_Geneva 11_Stockholm",
            "11_Stockholm 6_Geneva 14 11_Stockholm",
            "11_Stockholm 6_Geneva 7_Milan 8_Brussels 11_Stockholm",
            "11_Stockholm 8_Brussels 5_Madrid 0_Prague 11_Stockholm",
            "27 4_Dubai 6_Geneva 11_Stockholm",
            "28 23 11_Stockholm",
            "28 24 11_Stockholm",
            "28 12_Hong_Kong 23",
            "11_Stockholm 29 23",
            "11_Stockholm 13_Oslo 5_Madrid 0_Prague 11_Stockholm",
            "30 3_Copenhagen 3_Copenhagen 11_Stockholm",
            "11_Stockholm 6_Geneva 4_Dubai 21",
            "11_Stockholm 6_Geneva 13_Oslo 3_Copenhagen 11_Stockholm",
            "11_Stockholm 6_Geneva 15_New_York 6_Geneva 11_Stockholm",
            "11_Stockholm 0_Prague 16_New_York 0_Prague 11_Stockholm",
            "11_Stockholm 8_Brussels 14 11_Stockholm"
        ],
        "source": 11,
        "maxSeg": 5
    },
    "originalIGP": [
        9,
        7,
        9,
        9,
        9,
        9,
        9,
        9,
        9,
        9,
        9,
        8,
        8,
        10,
        8,
        9,
        7,
        9,
        9,
        9,
        9,
        9
    ],
    "newIGP": [
        5,
        5,
        5,
        5,
        5,
        7,
        5,
        5,
        7,
        7,
        5,
        7,
        5,
        7,
        5,
        7,
        7,
        5,
        7,
        7,
        5,
        7,
        5,
        7,
        7,
        7
    ],
    "newCover": {
        "cycles": [
            "0_Prague 1 0_Prague",
            "0_Prague 2_Hamburg 0_Prague 0_Prague",
            "0_Prague 6_Geneva 0_Prague 0_Prague",
            "0_Prague 5_Madrid 0_Prague 0_Prague",
            "0_Prague 3_Copenhagen 0_Prague 0_Prague",
            "0_Prague 2_Hamburg 10_Helsinki 0_Prague",
            "0_Prague 4_Dubai 0_Prague 0_Prague",
            "0_Prague 7_Milan 0_Prague 0_Prague",
            "0_Prague 6_Geneva 4_Dubai 0_Prague",
            "0_Prague 7_Milan 4_Dubai 0_Prague",
            "0_Prague 8_Brussels 0_Prague 0_Prague",
            "0_Prague 8_Brussels 5_Madrid 0_Prague",
            "0_Prague 10_Helsinki 0_Prague 0_Prague",
            "0_Prague 24 0_Prague",
            "0_Prague 12_Hong_Kong 0_Prague 0_Prague",
            "0_Prague 10_Helsinki 2_Hamburg 0_Prague",
            "0_Prague 29 0_Prague",
            "0_Prague 13_Oslo 0_Prague 0_Prague",
            "0_Prague 13_Oslo 4_Dubai 0_Prague",
            "0_Prague 4_Dubai 13_Oslo 0_Prague",
            "0_Prague 15_New_York 0_Prague 0_Prague",
            "0_Prague 4_Dubai 5_Madrid 0_Prague",
            "0_Prague 16_New_York 0_Prague 0_Prague",
            "0_Prague 4_Dubai 6_Geneva 0_Prague",
            "0_Prague 4_Dubai 7_Milan 0_Prague",
            "0_Prague 5_Madrid 8_Brussels 0_Prague"
        ],
        "source": 0,
        "runetime": 3663496,
        "maxSeg": 4
    }
}