{
    "initialCoverSize": 45,
    "times": [
        1552120,
        3134558,
        4811599,
        6712576,
        7820148,
        8813109,
        9820535,
        10738510,
        11647406,
        12587399,
        13502088,
        14432104,
        15483498,
        16585134,
        17661566,
        18726572,
        19812772,
        21718367,
        22939641,
        23885105,
        24846635
    ],
    "solution": [
        {
            "x": 0,
            "cycle": "0_PD 1_MI 0_PD 0_PD"
        },
        {
            "x": 0,
            "cycle": "0_PD 3_TS 0_PD 0_PD"
        },
        {
            "x": 0,
            "cycle": "0_PD 6_TO 0_PD 0_PD"
        },
        {
            "x": 0,
            "cycle": "0_PD 7_GE 0_PD 0_PD"
        },
        {
            "x": 0,
            "cycle": "0_PD 11_MI 0_PD 0_PD"
        },
        {
            "x": 0,
            "cycle": "0_PD 1_MI 2_PA 0_PD"
        },
        {
            "x": 0,
            "cycle": "0_PD 16_Ten155 0_PD 0_PD"
        },
        {
            "x": 0,
            "cycle": "0_PD 17_USA 0_PD 0_PD"
        },
        {
            "x": 0,
            "cycle": "0_PD 1_MI 12_RM 0_PD"
        },
        {
            "x": 0,
            "cycle": "0_PD 4_FI 0_PD 0_PD"
        },
        {
            "x": 0,
            "cycle": "0_PD 8_BO 0_PD 0_PD"
        },
        {
            "x": 0,
            "cycle": "0_PD 10_EsNet 0_PD 0_PD"
        },
        {
            "x": 0,
            "cycle": "0_PD 2_PA 0_PD 0_PD"
        },
        {
            "x": 0,
            "cycle": "0_PD 15_PI 0_PD 0_PD"
        },
        {
            "x": 0,
            "cycle": "0_PD 12_RM 0_PD 0_PD"
        },
        {
            "x": 0,
            "cycle": "0_PD 9_NA 0_PD 0_PD"
        },
        {
            "x": 0,
            "cycle": "0_PD 2_PA 1_MI 0_PD"
        },
        {
            "x": 0,
            "cycle": "0_PD 14_CT 0_PD 0_PD"
        },
        {
            "x": 0,
            "cycle": "0_PD 2_PA 12_RM 0_PD"
        },
        {
            "x": 0,
            "cycle": "0_PD 22_BA 0_PD 0_PD"
        },
        {
            "x": 0,
            "cycle": "0_PD 18_CA 0_PD 0_PD"
        },
        {
            "x": 0,
            "cycle": "0_PD 12_RM 1_MI 0_PD"
        },
        {
            "x": 0,
            "cycle": "0_PD 12_RM 2_PA 0_PD"
        },
        {
            "x": 0,
            "cycle": "0_PD 20_AQ 0_PD 0_PD"
        },
        {
            "x": 0,
            "cycle": "0_PD 21_FRA 0_PD 0_PD"
        },
        {
            "x": 0.12142857142857141,
            "cycle": "0_PD 9_NA 3_TS 9_NA 3_TS 9_NA 3_TS 9_NA 3_TS 0_PD"
        },
        {
            "x": 0.12142857142857141,
            "cycle": "0_PD 18_CA 6_TO 18_CA 6_TO 18_CA 6_TO 18_CA 6_TO 0_PD"
        },
        {
            "x": 0.2357142857142857,
            "cycle": "0_PD 20_AQ 14_CT 20_AQ 14_CT 20_AQ 14_CT 20_AQ 14_CT 0_PD"
        },
        {
            "x": 0.17857142857142855,
            "cycle": "0_PD 7_GE 21_FRA 7_GE 21_FRA 7_GE 21_FRA 7_GE 21_FRA 0_PD"
        },
        {
            "x": 0.19285714285714284,
            "cycle": "0_PD 11_MI 22_BA 11_MI 22_BA 11_MI 22_BA 11_MI 22_BA 0_PD"
        },
        {
            "x": 0.12142857142857141,
            "cycle": "0_PD 4_FI 2_PA 4_FI 2_PA 4_FI 2_PA 4_FI 2_PA 0_PD"
        },
        {
            "x": 0.15357142857142855,
            "cycle": "0_PD 10_EsNet 8_BO 10_EsNet 8_BO 10_EsNet 8_BO 10_EsNet 8_BO 0_PD"
        },
        {
            "x": 0.17142857142857143,
            "cycle": "0_PD 15_PI 12_RM 15_PI 12_RM 15_PI 12_RM 15_PI 12_RM 0_PD"
        },
        {
            "x": 0.21071428571428572,
            "cycle": "0_PD 17_USA 16_Ten155 17_USA 16_Ten155 17_USA 16_Ten155 17_USA 16_Ten155 0_PD"
        },
        {
            "x": 0,
            "cycle": "0_PD 4_FI 1_MI 4_FI 1_MI 4_FI 1_MI 4_FI 1_MI 0_PD"
        },
        {
            "x": 0.07857142857142857,
            "cycle": "0_PD 2_PA 12_RM 2_PA 12_RM 2_PA 12_RM 2_PA 12_RM 0_PD"
        },
        {
            "x": 0.1285714285714286,
            "cycle": "0_PD 6_TO 10_EsNet 6_TO 10_EsNet 6_TO 10_EsNet 6_TO 2_PA 0_PD"
        },
        {
            "x": 0.1285714285714286,
            "cycle": "0_PD 9_NA 18_CA 9_NA 18_CA 9_NA 18_CA 9_NA 18_CA 0_PD"
        },
        {
            "x": 0.1285714285714286,
            "cycle": "0_PD 4_FI 3_TS 4_FI 3_TS 4_FI 3_TS 4_FI 3_TS 0_PD"
        },
        {
            "x": 0.07142857142857144,
            "cycle": "0_PD 7_GE 8_BO 7_GE 8_BO 7_GE 8_BO 2_PA 7_GE 0_PD"
        },
        {
            "x": 0.05714285714285715,
            "cycle": "0_PD 11_MI 8_BO 11_MI 8_BO 14_CT 21_FRA 8_BO 11_MI 0_PD"
        },
        {
            "x": 0.05714285714285715,
            "cycle": "0_PD 22_BA 21_FRA 22_BA 21_FRA 22_BA 21_FRA 22_BA 21_FRA 0_PD"
        },
        {
            "x": 0.039285714285714285,
            "cycle": "0_PD 17_USA 15_PI 17_USA 15_PI 17_USA 15_PI 17_USA 15_PI 0_PD"
        },
        {
            "x": 0.039285714285714285,
            "cycle": "0_PD 16_Ten155 15_PI 16_Ten155 15_PI 16_Ten155 15_PI 16_Ten155 15_PI 0_PD"
        },
        {
            "x": 0.014285714285714287,
            "cycle": "0_PD 11_MI 20_AQ 11_MI 20_AQ 11_MI 20_AQ 11_MI 20_AQ 0_PD"
        }
    ],
    "values": [
        22,
        18.333333333333332,
        14.666666666666668,
        11.916666666666668,
        10.208333333333334,
        8.5,
        7.5,
        5.75,
        4.083333333333334,
        2.583333333333333,
        2.395833333333333,
        2.3125,
        2.3125,
        2.3125,
        2.2874999999999996,
        2.2784090909090913,
        2.274671052631579,
        2.261029411764706,
        2.261029411764706,
        2.251838235294118,
        2.249999999999999
    ],
    "initialCoverSeg": 4,
    "runtime": 226774,
    "lpBound": 2.249999999999999
}