{
    "initialCoverSize": 31,
    "times": [
        1235247,
        2171265,
        3122695,
        4097289,
        5010798,
        5926574,
        6882012,
        7797739,
        8719310,
        9643522,
        10584803,
        11520275,
        12417841,
        13358580,
        14277577,
        15224673
    ],
    "solution": [
        {
            "x": 0,
            "cycle": "0_Kherson 1_Mykolaiv,0_Kherson 0_Kherson"
        },
        {
            "x": 0,
            "cycle": "0_Kherson 2_Sevastopol 0_Kherson 0_Kherson"
        },
        {
            "x": 0,
            "cycle": "0_Kherson 4_Vinnitsa 0_Kherson 0_Kherson"
        },
        {
            "x": 0,
            "cycle": "0_Kherson 6_Odessa 0_Kherson 0_Kherson"
        },
        {
            "x": 0,
            "cycle": "0_Kherson 4_Vinnitsa 5_Khmelnitsky 0_Kherson"
        },
        {
            "x": 0,
            "cycle": "0_Kherson 5_Khmelnitsky 4_Vinnitsa 0_Kherson"
        },
        {
            "x": 0,
            "cycle": "0_Kherson 11_Odessa-IX 0_Kherson 0_Kherson"
        },
        {
            "x": 0,
            "cycle": "0_Kherson 7_Kamianets-Podilsky 0_Kherson 0_Kherson"
        },
        {
            "x": 0,
            "cycle": "0_Kherson 8_Frankfurt_(Internet) 0_Kherson 0_Kherson"
        },
        {
            "x": 0,
            "cycle": "0_Kherson 9_Poznan_(GEANT_&_Internet) 0_Kherson 0_Kherson"
        },
        {
            "x": 0,
            "cycle": "0_Kherson 12_Kharkiv-IX 0_Kherson 0_Kherson"
        },
        {
            "x": 0,
            "cycle": "0_Kherson 13_UA-IX 0_Kherson 0_Kherson"
        },
        {
            "x": 0,
            "cycle": "0_Kherson 14_Zaporizhia 0_Kherson 0_Kherson"
        },
        {
            "x": 0,
            "cycle": "0_Kherson 23_Donetsk 0_Kherson 0_Kherson"
        },
        {
            "x": 0,
            "cycle": "0_Kherson 17_Lutsk 0_Kherson 0_Kherson"
        },
        {
            "x": 0,
            "cycle": "0_Kherson 20_Pereyaslav 0_Kherson 0_Kherson"
        },
        {
            "x": 0.10416666666666667,
            "cycle": "0_Kherson 7_Kamianets-Podilsky 2_Sevastopol 7_Kamianets-Podilsky 2_Sevastopol 7_Kamianets-Podilsky 2_Sevastopol 7_Kamianets-Podilsky 2_Sevastopol 0_Kherson"
        },
        {
            "x": 0.25,
            "cycle": "0_Kherson 9_Poznan_(GEANT_&_Internet) 8_Frankfurt_(Internet) 9_Poznan_(GEANT_&_Internet) 8_Frankfurt_(Internet) 9_Poznan_(GEANT_&_Internet) 8_Frankfurt_(Internet) 9_Poznan_(GEANT_&_Internet) 8_Frankfurt_(Internet) 0_Kherson"
        },
        {
            "x": 0.25,
            "cycle": "0_Kherson 12_Kharkiv-IX 11_Odessa-IX 12_Kharkiv-IX 11_Odessa-IX 12_Kharkiv-IX 11_Odessa-IX 12_Kharkiv-IX 11_Odessa-IX 0_Kherson"
        },
        {
            "x": 0.25,
            "cycle": "0_Kherson 14_Zaporizhia 13_UA-IX 14_Zaporizhia 13_UA-IX 14_Zaporizhia 13_UA-IX 14_Zaporizhia 13_UA-IX 0_Kherson"
        },
        {
            "x": 0.25,
            "cycle": "0_Kherson 20_Pereyaslav 17_Lutsk 20_Pereyaslav 17_Lutsk 20_Pereyaslav 17_Lutsk 20_Pereyaslav 17_Lutsk 0_Kherson"
        },
        {
            "x": 0.25,
            "cycle": "0_Kherson 5_Khmelnitsky 4_Vinnitsa 5_Khmelnitsky 4_Vinnitsa 5_Khmelnitsky 4_Vinnitsa 5_Khmelnitsky 4_Vinnitsa 0_Kherson"
        },
        {
            "x": 0.1875,
            "cycle": "0_Kherson 23_Donetsk 4_Vinnitsa 23_Donetsk 4_Vinnitsa 23_Donetsk 4_Vinnitsa 23_Donetsk 4_Vinnitsa 0_Kherson"
        },
        {
            "x": 0.08333333333333333,
            "cycle": "0_Kherson 5_Khmelnitsky 2_Sevastopol 5_Khmelnitsky 2_Sevastopol 5_Khmelnitsky 2_Sevastopol 5_Khmelnitsky 2_Sevastopol 0_Kherson"
        },
        {
            "x": 0.08333333333333333,
            "cycle": "0_Kherson 4_Vinnitsa 5_Khmelnitsky 7_Kamianets-Podilsky 4_Vinnitsa 5_Khmelnitsky 7_Kamianets-Podilsky 4_Vinnitsa 5_Khmelnitsky 0_Kherson"
        },
        {
            "x": 0.10416666666666667,
            "cycle": "0_Kherson 7_Kamianets-Podilsky 5_Khmelnitsky 7_Kamianets-Podilsky 5_Khmelnitsky 7_Kamianets-Podilsky 5_Khmelnitsky 7_Kamianets-Podilsky 5_Khmelnitsky 0_Kherson"
        },
        {
            "x": 0,
            "cycle": "0_Kherson 11_Odessa-IX 8_Frankfurt_(Internet) 11_Odessa-IX 8_Frankfurt_(Internet) 11_Odessa-IX 8_Frankfurt_(Internet) 11_Odessa-IX 8_Frankfurt_(Internet) 0_Kherson"
        },
        {
            "x": 0,
            "cycle": "0_Kherson 11_Odessa-IX 9_Poznan_(GEANT_&_Internet) 11_Odessa-IX 9_Poznan_(GEANT_&_Internet) 11_Odessa-IX 9_Poznan_(GEANT_&_Internet) 11_Odessa-IX 9_Poznan_(GEANT_&_Internet) 0_Kherson"
        },
        {
            "x": 0,
            "cycle": "0_Kherson 17_Lutsk 13_UA-IX 17_Lutsk 13_UA-IX 17_Lutsk 13_UA-IX 17_Lutsk 13_UA-IX 0_Kherson"
        },
        {
            "x": 0,
            "cycle": "0_Kherson 20_Pereyaslav 13_UA-IX 20_Pereyaslav 13_UA-IX 20_Pereyaslav 13_UA-IX 20_Pereyaslav 13_UA-IX 0_Kherson"
        },
        {
            "x": 0.0625,
            "cycle": "0_Kherson 23_Donetsk 2_Sevastopol 23_Donetsk 2_Sevastopol 23_Donetsk 2_Sevastopol 23_Donetsk 2_Sevastopol 0_Kherson"
        }
    ],
    "values": [
        13,
        11.25,
        9.5,
        7.75,
        6,
        4.25,
        4.25,
        3.5,
        2.083333333333333,
        1.9791666666666667,
        1.90625,
        1.90625,
        1.90625,
        1.90625,
        1.90625,
        1.875
    ],
    "initialCoverSeg": 4,
    "runtime": 206234,
    "lpBound": 1.875
}